{
  "$schema": "http://json-schema.org/draft-07/schema#",
  "$id": "https://protocol.peopleaquarius.com/schemas/identity-record",
  "title": "PLN Identity Record",
  "type": "object",
  "required": ["id", "type", "auth", "trust_level", "autonomy_setting", "delegation_chain", "preferences", "risk_profile"],
  "additionalProperties": false,
  "properties": {
    "id": { "type": "string" },
    "type": { "type": "string", "enum": ["human", "agent", "platform"] },
    "auth": {
      "type": "object",
      "required": ["method", "verified"],
      "properties": {
        "method": { "type": "string" },
        "verified": { "type": "boolean" }
      }
    },
    "trust_level": { "type": "string", "enum": ["unverified", "community-verified", "platform-verified", "government-verified"] },
    "autonomy_setting": { "type": "string", "enum": ["advisor", "facilitator", "agent", "delegate"] },
    "delegation_chain": { "type": "array", "items": { "type": "string" } },
    "preferences": { "type": "object" },
    "risk_profile": {
      "type": "object",
      "required": ["max_auto_commit_value", "max_auto_commit_currency", "restricted_categories", "approval_rules"],
      "properties": {
        "max_auto_commit_value": { "type": "number" },
        "max_auto_commit_currency": { "type": "string" },
        "restricted_categories": { "type": "array", "items": { "type": "string" } },
        "approval_rules": { "type": "object" }
      }
    }
  }
}
